anls_star/__init__.py
anls_star/anls_star.py
anls_star/key_scores_utils.py
anls_star-0.0.12.dist-info/METADATA
anls_star-0.0.12.dist-info/WHEEL
anls_star-0.0.12.dist-info/licenses/LICENSE
anls_star-0.0.12.dist-info/RECORD
