Metadata-Version: 2.4
Name: anls_star
Version: 0.0.12
Summary: A universal metric for Generative Large Language Models (GLLMs)
Project-URL: Repository, https://github.com/deepopinion/anls_star_metric
Project-URL: Issues, https://github.com/deepopinion/anls_star_metric/issues
Project-URL: Paper, https://arxiv.org/abs/2402.03848
Project-URL: DeepOpinion, https://deepopinion.ai
Author-email: David Peer <david.peer@deepopinion.ai>
License-File: LICENSE
Classifier: License :: OSI Approved :: Apache Software License
Classifier: Operating System :: OS Independent
Classifier: Programming Language :: Python :: 3
Requires-Python: >=3.8
Requires-Dist: munkres
